{
  "attributesForFaceting": [
    "audience",
    "filterOnly(canonical_target)",
    "category",
    "family",
    "lang",
    "language",
    "method_type",
    "operation_id",
    "page_type",
    "surface",
    "transport",
    "type",
    "version"
  ],
  "attributesToRetrieve": [
    "hierarchy",
    "content",
    "anchor",
    "url",
    "url_without_anchor",
    "type",
    "category",
    "method_type",
    "surface",
    "family",
    "audience",
    "page_type",
    "transport",
    "operation_id",
    "canonical_target",
    "keywords"
  ],
  "attributesToHighlight": [
    "hierarchy",
    "content"
  ],
  "attributesToSnippet": [
    "content:14"
  ],
  "camelCaseAttributes": [
    "hierarchy",
    "content"
  ],
  "searchableAttributes": [
    "unordered(operation_id)",
    "unordered(keywords)",
    "unordered(hierarchy.lvl1)",
    "unordered(hierarchy.lvl2)",
    "unordered(hierarchy.lvl3)",
    "unordered(hierarchy.lvl4)",
    "unordered(hierarchy.lvl5)",
    "unordered(hierarchy.lvl6)",
    "unordered(hierarchy.lvl0)",
    "content"
  ],
  "distinct": true,
  "attributeForDistinct": "url_without_anchor",
  "customRanking": [
    "desc(weight.pageRank)",
    "desc(weight.level)",
    "asc(weight.position)"
  ],
  "ranking": [
    "words",
    "filters",
    "typo",
    "attribute",
    "proximity",
    "exact",
    "custom"
  ],
  "highlightPreTag": "<span class=\"algolia-docsearch-suggestion--highlight\">",
  "highlightPostTag": "</span>",
  "minWordSizefor1Typo": 3,
  "minWordSizefor2Typos": 7,
  "allowTyposOnNumericTokens": false,
  "minProximity": 1,
  "ignorePlurals": ["en", "ru"],
  "advancedSyntax": true,
  "attributeCriteriaComputedByMinProximity": true,
  "removeWordsIfNoResults": "allOptional",
  "separatorsToIndex": "_"
}
